ccxt/__init__.py
ccxt/abantether.py
ccxt/afratether.py
ccxt/alpaca.py
ccxt/apex.py
ccxt/arzinja.py
ccxt/arzplus.py
ccxt/ascendex.py
ccxt/bequant.py
ccxt/bigone.py
ccxt/binance.py
ccxt/binancecoinm.py
ccxt/binanceus.py
ccxt/binanceusdm.py
ccxt/bingx.py
ccxt/bit24.py
ccxt/bit2c.py
ccxt/bitbank.py
ccxt/bitbarg.py
ccxt/bitbns.py
ccxt/bitfinex.py
ccxt/bitflyer.py
ccxt/bitget.py
ccxt/bithumb.py
ccxt/bitimen.py
ccxt/bitir.py
ccxt/bitmart.py
ccxt/bitmex.py
ccxt/bitopro.py
ccxt/bitpin.py
ccxt/bitrue.py
ccxt/bitso.py
ccxt/bitstamp.py
ccxt/bitteam.py
ccxt/bittrade.py
ccxt/bitunix.py
ccxt/bitvavo.py
ccxt/blockchaincom.py
ccxt/blofin.py
ccxt/btcalpha.py
ccxt/btcbox.py
ccxt/btcmarkets.py
ccxt/btcturk.py
ccxt/bybit.py
ccxt/bydfi.py
ccxt/cafearz.py
ccxt/cex.py
ccxt/coinbase.py
ccxt/coinbaseadvanced.py
ccxt/coinbaseexchange.py
ccxt/coinbaseinternational.py
ccxt/coincatch.py
ccxt/coincheck.py
ccxt/coinex.py
ccxt/coinmate.py
ccxt/coinmetro.py
ccxt/coinone.py
ccxt/coinsph.py
ccxt/coinspot.py
ccxt/cryptocom.py
ccxt/cryptomus.py
ccxt/defx.py
ccxt/delta.py
ccxt/deribit.py
ccxt/derive.py
ccxt/digifinex.py
ccxt/ellipx.py
ccxt/eterex.py
ccxt/excoino.py
ccxt/exir.py
ccxt/exmo.py
ccxt/exnovin.py
ccxt/farhadexchange.py
ccxt/fmfwio.py
ccxt/foxbit.py
ccxt/gate.py
ccxt/gateio.py
ccxt/gemini.py
ccxt/hamtapay.py
ccxt/hashkey.py
ccxt/hibachi.py
ccxt/hitbtc.py
ccxt/hitobit.py
ccxt/hollaex.py
ccxt/htx.py
ccxt/huobi.py
ccxt/hyperliquid.py
ccxt/independentreserve.py
ccxt/indodax.py
ccxt/jibitex.py
ccxt/kcex.py
ccxt/kifpoolme.py
ccxt/kraken.py
ccxt/krakenfutures.py
ccxt/kucoin.py
ccxt/kucoinfutures.py
ccxt/latoken.py
ccxt/lbank.py
ccxt/luno.py
ccxt/mazdax.py
ccxt/mercado.py
ccxt/mexc.py
ccxt/modetrade.py
ccxt/myokx.py
ccxt/ndax.py
ccxt/nobitex.py
ccxt/novadax.py
ccxt/oceanex.py
ccxt/okcoin.py
ccxt/okexchange.py
ccxt/okx.py
ccxt/okxus.py
ccxt/ompfinex.py
ccxt/onetrading.py
ccxt/oxfun.py
ccxt/p2b.py
ccxt/paradex.py
ccxt/paymium.py
ccxt/phemex.py
ccxt/pingi.py
ccxt/poloniex.py
ccxt/pooleno.py
ccxt/probit.py
ccxt_ir-4.9.10.dist-info/licenses/LICENSE.txt
ccxt_ir-4.9.10.dist-info/METADATA
ccxt_ir-4.9.10.dist-info/WHEEL
ccxt_ir-4.9.10.dist-info/top_level.txt
ccxt_ir-4.9.10.dist-info/RECORD
